{
  "sections": {
    "main": {
      "type": "main-product",
      "blocks": {
        "vendor": {
          "type": "vendor",
          "settings": {
          }
        },
        "title": {
          "type": "title",
          "settings": {
            "heading_tag": "h4"
          }
        },
        "price": {
          "type": "price",
          "settings": {
            "show_taxes_notice": false
          }
        },
        "payment_terms": {
          "type": "payment_terms",
          "settings": {
          }
        },
        "dd90a88b-e545-4a50-85ee-cd5fb5ace1ef": {
          "type": "shopify:\/\/apps\/\/blocks\/app-block\/67cce3d8-a1e5-43f3-8d2d-0c320d8c46e7",
          "settings": {
            "onetime_purchase_label": "通常注文",
            "subscription_label": "定期購入"
          }
        },
        "variant_picker": {
          "type": "variant_picker",
          "settings": {
            "hide_sold_out_variants": false,
            "selector_type": "block",
            "color_selector_type": "block",
            "size_chart_page": ""
          }
        },
        "quantity_selector": {
          "type": "quantity_selector",
          "settings": {
          }
        },
        "buy_buttons": {
          "type": "buy_buttons",
          "settings": {
            "show_payment_button": true,
            "show_gift_card_recipient": false,
            "atc_button_background": "",
            "atc_button_text_color": "",
            "payment_button_background": "#006428",
            "payment_button_text_color": "#ffffff"
          }
        },
        "complementary_products": {
          "type": "complementary_products",
          "settings": {
            "title": "Pairs well with",
            "products_count": 2,
            "show_below_gallery": true,
            "stack_products": false,
            "show_quick_buy": true
          }
        },
        "d1aea2fc-59ab-4836-a57a-8c8a13ed145e": {
          "type": "shopify:\/\/apps\/\/blocks\/app-block\/8c410064-0703-476d-add4-f33699a7cbf7",
          "settings": {
          }
        },
        "separator": {
          "type": "separator",
          "settings": {
          }
        },
        "description": {
          "type": "description",
          "settings": {
            "collapse_content": false,
            "show_below_gallery": false
          }
        },
        "d92afbf0-2406-4b78-87e5-477795a5d14c": {
          "type": "popup",
          "settings": {
            "link_text": "商品詳細",
            "popup_page": "メディバーム-happy-up"
          }
        }
      },
      "block_order": [
        "vendor",
        "title",
        "price",
        "payment_terms",
        "dd90a88b-e545-4a50-85ee-cd5fb5ace1ef",
        "variant_picker",
        "quantity_selector",
        "buy_buttons",
        "complementary_products",
        "d1aea2fc-59ab-4836-a57a-8c8a13ed145e",
        "separator",
        "description",
        "d92afbf0-2406-4b78-87e5-477795a5d14c"
      ],
      "custom_css": [

      ],
      "settings": {
        "container_size": "lg",
        "product_info_size": 55,
        "show_sticky_add_to_cart": false,
        "center_basic_info": true,
        "desktop_media_layout": "grid_2x_highlighted",
        "desktop_media_grid_gap": 30,
        "mobile_controls": "dots",
        "enable_media_autoplay": false,
        "enable_video_looping": true,
        "enable_image_zoom": true,
        "max_image_zoom_level": 3
      }
    },
    "eb5bc90c-f520-4d0d-ab9c-17716b32cbe2": {
      "type": "image-with-text",
      "blocks": {
        "template--19587106603313__eb5bc90c-f520-4d0d-ab9c-17716b32cbe2-1687340750ba783fb3-2": {
          "type": "richtext",
          "settings": {
            "content": "<p><strong>あなたを愛するペットのためにペットが好む、安心なアロマの香り。人もペットも一緒に使えるアロママッサージバーム。<\/strong><\/p>"
          }
        },
        "2408536c-f6dc-4c0f-bc97-405f039023c7": {
          "type": "richtext",
          "settings": {
            "content": "<p>ハンドクリームをつけた後にペットに触るのをためらったことはありませんか？<\/p><p>オーガニックでステキなコスメであっても、その香りがペットが嫌いな香りだと、鼻がいいペットにとっては、大好きなママの香りを遠避けたくなってしまいます。<\/p><p>メディバームは、100%天然アロマオイルを配合した、心地良い香りのアロママッサージバームです。<\/p>"
          }
        }
      },
      "block_order": [
        "template--19587106603313__eb5bc90c-f520-4d0d-ab9c-17716b32cbe2-1687340750ba783fb3-2",
        "2408536c-f6dc-4c0f-bc97-405f039023c7"
      ],
      "settings": {
        "separate_section_with_border": true,
        "image": "shopify:\/\/shop_images\/medi_1_535x_eb45bf57-f31e-4c03-98ca-86231725fc00.jpg",
        "reveal_on_scroll": false,
        "image_position": "start",
        "content_width": "md",
        "remove_vertical_spacing": false
      }
    },
    "234ae6c0-959d-4e56-9bd8-a656dd319739": {
      "type": "multi-column",
      "blocks": {
        "template--19587106603313__234ae6c0-959d-4e56-9bd8-a656dd319739-1687340973eb39e67a-0": {
          "type": "image_with_text",
          "settings": {
            "image": "shopify:\/\/shop_images\/medi_4_550x_63b85015-7a28-4972-a424-43f8dc3fc01f.webp",
            "title": "",
            "heading_tag": "h3",
            "content": "<p><strong>北海道のたもぎ茸由来のセラミドをっぷり配合。保湿効果、バリア機能を期待できます。<\/strong><\/p>",
            "link_url": "",
            "link_text": ""
          }
        },
        "template--19587106603313__234ae6c0-959d-4e56-9bd8-a656dd319739-1687340973eb39e67a-1": {
          "type": "image_with_text",
          "settings": {
            "image": "shopify:\/\/shop_images\/medi_5_550x_d105d1a3-c339-401e-947b-313242dcb2e9.webp",
            "title": "",
            "heading_tag": "h3",
            "content": "<p><strong>ペットの性格や気持ちに合わせて、数種類の100%天然アロマオイルをブレンドした、２タイプをご用意。マッサージにより、さらに心身へのアロマ効果をもたらします。<\/strong><\/p>",
            "link_url": "",
            "link_text": ""
          }
        },
        "template--19587106603313__234ae6c0-959d-4e56-9bd8-a656dd319739-1687340973eb39e67a-2": {
          "type": "image_with_text",
          "settings": {
            "image": "shopify:\/\/shop_images\/medi_6_550x_95ddae25-a333-4eaa-8b41-2bdcc686cf89.webp",
            "title": "",
            "heading_tag": "h3",
            "content": "<p><strong>肌になじみやすい、さらっとした使用感。肌へもペットの被毛へも、うるおいとサラサラ感を、心地よく感じて頂けます。<\/strong><\/p>",
            "link_url": "",
            "link_text": ""
          }
        }
      },
      "block_order": [
        "template--19587106603313__234ae6c0-959d-4e56-9bd8-a656dd319739-1687340973eb39e67a-0",
        "template--19587106603313__234ae6c0-959d-4e56-9bd8-a656dd319739-1687340973eb39e67a-1",
        "template--19587106603313__234ae6c0-959d-4e56-9bd8-a656dd319739-1687340973eb39e67a-2"
      ],
      "custom_css": [
        ".container {max-width: 1000px; margin: 0 auto;}"
      ],
      "settings": {
        "separate_section_with_border": false,
        "columns_per_row": 3,
        "stack_on_mobile": false,
        "overlap_image": false,
        "content_alignment": "start",
        "text_alignment": "start",
        "spacing": "md",
        "subheading": "",
        "title": "",
        "content": ""
      }
    },
    "98a5ed89-f97e-4243-b1fb-b8ae698aff3b": {
      "type": "image-with-text-overlay",
      "settings": {
        "image_size": "auto",
        "image": "shopify:\/\/shop_images\/medi_7_710x_19aa8f40-f185-47f3-8864-aaa78f462c84.webp",
        "allow_transparent_header": false,
        "reveal_on_scroll": false,
        "remove_vertical_spacing": false,
        "content_width": "sm",
        "mobile_text_position": "place-self-center text-center",
        "desktop_text_position": "sm:place-self-center sm:text-center",
        "text_color": "#ffffff",
        "overlay_color": "#000000",
        "overlay_opacity": 0
      }
    },
    "related-products": {
      "type": "related-products",
      "custom_css": [

      ],
      "settings": {
        "separate_section_with_border": true,
        "hide_product_information": false,
        "stack_products": false,
        "recommendations_count": 10,
        "products_per_row_mobile": "2",
        "products_per_row_desktop": 4,
        "horizontal_spacing_factor": 1,
        "vertical_spacing_factor": 1,
        "subheading": "Related Items",
        "title": "関連商品",
        "content": ""
      }
    },
    "700c6d21-c325-4462-b507-4e1b0c90fc32": {
      "type": "recently-viewed-products",
      "settings": {
        "separate_section_with_border": true,
        "hide_product_information": false,
        "stack_products": false,
        "products_count": 9,
        "products_per_row_mobile": "2",
        "products_per_row_desktop": 4,
        "horizontal_spacing_factor": 1,
        "vertical_spacing_factor": 1,
        "subheading": "Checked Items",
        "title": "最近チェックした商品",
        "content": ""
      }
    }
  },
  "order": [
    "main",
    "eb5bc90c-f520-4d0d-ab9c-17716b32cbe2",
    "234ae6c0-959d-4e56-9bd8-a656dd319739",
    "98a5ed89-f97e-4243-b1fb-b8ae698aff3b",
    "related-products",
    "700c6d21-c325-4462-b507-4e1b0c90fc32"
  ]
}
